beam_pyspark_runner/__init__.py
beam_pyspark_runner/eval_context.py
beam_pyspark_runner/evaluator.py
beam_pyspark_runner/execution_plan.py
beam_pyspark_runner/overrides.py
beam_pyspark_runner/pyspark_runner.py
beam_pyspark_runner/pyspark_visitors.py
beam_pyspark_runner/transform_evaluators.py
beam_pyspark_runner/version.py
beam_pyspark_runner-0.0.3.dist-info/LICENSE
beam_pyspark_runner-0.0.3.dist-info/METADATA
beam_pyspark_runner-0.0.3.dist-info/WHEEL
beam_pyspark_runner-0.0.3.dist-info/top_level.txt
beam_pyspark_runner-0.0.3.dist-info/RECORD
