Metadata-Version: 2.1
Name: beam-pyspark-runner
Version: 0.0.3
Summary: An Apache Beam pipeline Runner built on Apache Spark's python API
Author-email: Nathan Zimmerman <npzimmerman@gmail.com>
License: MIT
Project-URL: homepage, https://github.com/moradology/beam-pyspark-runner
Project-URL: repository, https://github.com/moradology/beam-pyspark-runner.git
Keywords: virtualenv,dependencies
Classifier: Intended Audience :: Developers
Classifier: Intended Audience :: Information Technology
Classifier: Intended Audience :: Science/Research
Classifier: Programming Language :: Python :: 3.8
Classifier: Programming Language :: Python :: 3.9
Classifier: Programming Language :: Python :: 3.10
Classifier: Programming Language :: Python :: 3.11
Classifier: Programming Language :: Python :: 3.12
Classifier: License :: OSI Approved :: MIT License
Requires-Python: >=3.7
License-File: LICENSE
Requires-Dist: apache-beam ==2.48.0
Requires-Dist: pyspark ==3.5.1
Requires-Dist: psutil ==5.9.8
Provides-Extra: dev
Requires-Dist: pytest >=8.0.0 ; extra == 'dev'
Requires-Dist: pytest-cov >=4.1.0 ; extra == 'dev'
Provides-Extra: lint
Requires-Dist: black >=23.9.1 ; extra == 'lint'
Requires-Dist: isort >=5.13.0 ; extra == 'lint'
Requires-Dist: flake8 >=7.0.0 ; extra == 'lint'
Requires-Dist: Flake8-pyproject >=1.2.3 ; extra == 'lint'
Requires-Dist: mypy >=1.8.0 ; extra == 'lint'
Requires-Dist: pre-commit >=3.4.0 ; extra == 'lint'
Requires-Dist: pytest >=8.0.0 ; extra == 'lint'
Requires-Dist: pytest-cov >=4.1.0 ; extra == 'lint'
Requires-Dist: tox >=4.11.3 ; extra == 'lint'
